azure_recommendations_10/__init__.py
azure_recommendations_10/recommendation/__init__.py
azure_recommendations_10/recommendation/advisor_recommendations.py
azure_recommendations_10/recommendation/network_recommendations.py
azure_recommendations_10/recommendation/utils.py
azure_recommendations_10/recommendation/vm_recommendations.py
azure_recommendations_10-0.2.0.dist-info/LICENCE
azure_recommendations_10-0.2.0.dist-info/METADATA
azure_recommendations_10-0.2.0.dist-info/WHEEL
azure_recommendations_10-0.2.0.dist-info/top_level.txt
azure_recommendations_10-0.2.0.dist-info/RECORD
